{
  "$schema": "../../../node_modules/@microsoft/sp-module-interfaces/lib/manifestSchemas/jsonSchemas/clientSideComponentManifestSchema.json",

  "id": "c93b1975-437d-4f41-abf4-6307841097fd",
  "alias": "PaitSliderSpFxWebPart",
  "componentType": "WebPart",
  "version": "0.0.1",
  "manifestVersion": 2,

  "preconfiguredEntries": [{
    "groupId": "c93b1975-437d-4f41-abf4-6307841097fd",
    "group": { "default": "Under Development" },
    "title": { "default": "PAITSliderSPFx" },
    "description": { "default": "Turn a Promted Links list in SharePoint into a Content Slider with Unslider" },
    "officeFabricIconFontName": "Page",
    "properties": {
      "ListName": "PromotedLinks",
      "ViewName": "All Promoted Links",
      "CustomCSS": "",
      "Next": ">",
      "Previous": "<",
      "Arrows": true
    }
  }]
}
